zep/__init__.py
zep-0.0.1.dist-info/METADATA
zep-0.0.1.dist-info/WHEEL
zep-0.0.1.dist-info/licenses/LICENSE
zep-0.0.1.dist-info/RECORD
