Metadata-Version: 2.4
Name: zep
Version: 0.0.1
Summary: zed wrapped in Python
Author-email: Lex Berezhny <lex@damoti.com>
License-File: LICENSE
Requires-Python: >=3.12
